spaceone/__init__.py
spaceone/core/__init__.py
spaceone/core/base.py
spaceone/core/command.py
spaceone/core/error.py
spaceone/core/locator.py
spaceone/core/manager.py
spaceone/core/token.py
spaceone/core/transaction.py
spaceone/core/utils.py
spaceone/core/auth/__init__.py
spaceone/core/auth/jwt/__init__.py
spaceone/core/auth/jwt/jwt_util.py
spaceone/core/cache/__init__.py
spaceone/core/cache/base_cache.py
spaceone/core/cache/local_cache.py
spaceone/core/cache/redis_cache.py
spaceone/core/config/__init__.py
spaceone/core/config/default_conf.py
spaceone/core/connector/__init__.py
spaceone/core/connector/space_connector.py
spaceone/core/fastapi/__init__.py
spaceone/core/fastapi/api.py
spaceone/core/fastapi/server.py
spaceone/core/fastapi/extension/__init__.py
spaceone/core/fastapi/extension/health.py
spaceone/core/fastapi/extension/reflection.py
spaceone/core/handler/__init__.py
spaceone/core/handler/authentication_handler.py
spaceone/core/handler/authorization_handler.py
spaceone/core/handler/mutation_handler.py
spaceone/core/logger/__init__.py
spaceone/core/logger/filters/__init__.py
spaceone/core/logger/filters/error.py
spaceone/core/logger/filters/exclude.py
spaceone/core/logger/filters/masking.py
spaceone/core/logger/filters/message.py
spaceone/core/logger/filters/parameter.py
spaceone/core/logger/filters/traceback.py
spaceone/core/logger/filters/transaction.py
spaceone/core/model/__init__.py
spaceone/core/model/base_model.py
spaceone/core/model/mongo_model/__init__.py
spaceone/core/model/mongo_model/filter_operator.py
spaceone/core/model/mongo_model/stat_operator.py
spaceone/core/opentelemetry/__init__.py
spaceone/core/opentelemetry/metrics.py
spaceone/core/opentelemetry/tracer.py
spaceone/core/plugin/__init__.py
spaceone/core/plugin/plugin_conf.py
spaceone/core/plugin/server.py
spaceone/core/pygrpc/__init__.py
spaceone/core/pygrpc/api.py
spaceone/core/pygrpc/client.py
spaceone/core/pygrpc/message_type.py
spaceone/core/pygrpc/server.py
spaceone_core-2.0.144.dist-info/METADATA
spaceone_core-2.0.144.dist-info/WHEEL
spaceone_core-2.0.144.dist-info/entry_points.txt
spaceone_core-2.0.144.dist-info/top_level.txt
spaceone_core-2.0.144.dist-info/RECORD
