Metadata-Version: 2.1
Name: spaceone-core
Version: 2.0.144
Summary: Cloudforet Core Library
Home-page: https://cloudforet.io/
Author: MEGAZONE Cloud Corp.
Author-email: admin@spaceone.dev
License: Apache License 2.0
Platform: UNKNOWN
Requires-Dist: protobuf==3.*
Requires-Dist: grpcio-reflection
Requires-Dist: google-api-core
Requires-Dist: grpcio-health-checking
Requires-Dist: pydantic==1.*
Requires-Dist: mongoengine
Requires-Dist: fastapi
Requires-Dist: fastapi-utils
Requires-Dist: uvicorn
Requires-Dist: asyncio
Requires-Dist: PyYAML
Requires-Dist: jsonschema
Requires-Dist: schedule
Requires-Dist: scheduler-cron
Requires-Dist: redis
Requires-Dist: cachetools
Requires-Dist: pycryptodome
Requires-Dist: jwcrypto
Requires-Dist: python-dateutil
Requires-Dist: python-consul
Requires-Dist: dnspython
Requires-Dist: requests
Requires-Dist: click
Requires-Dist: boto3
Requires-Dist: unittest-xml-reporting
Requires-Dist: factory-boy
Requires-Dist: mongomock
Requires-Dist: opentelemetry-api
Requires-Dist: opentelemetry-sdk
Requires-Dist: opentelemetry-exporter-otlp-proto-grpc
Requires-Dist: opentelemetry-instrumentation-logging
Requires-Dist: opentelemetry-exporter-prometheus
